mable/__init__.py
mable/__main__.py
mable/_about.py
mable/_testnd.py
mable/applications.py
mable/audit_logs.py
mable/channels.py
mable/cli.py
mable/colors.py
mable/colours.py
mable/commands.py
mable/components.py
mable/embeds.py
mable/emojis.py
mable/errors.py
mable/files.py
mable/guilds.py
mable/intents.py
mable/invites.py
mable/iterators.py
mable/locales.py
mable/messages.py
mable/permissions.py
mable/presences.py
mable/scheduled_events.py
mable/sessions.py
mable/snowflakes.py
mable/stickers.py
mable/templates.py
mable/traits.py
mable/undefined.py
mable/urls.py
mable/users.py
mable/voices.py
mable/webhooks.py
mable/api/__init__.py
mable/api/cache.py
mable/api/config.py
mable/api/entity_factory.py
mable/api/event_factory.py
mable/api/event_manager.py
mable/api/interaction_server.py
mable/api/rest.py
mable/api/shard.py
mable/api/special_endpoints.py
mable/api/voice.py
mable/events/__init__.py
mable/events/application_events.py
mable/events/base_events.py
mable/events/channel_events.py
mable/events/guild_events.py
mable/events/interaction_events.py
mable/events/lifetime_events.py
mable/events/member_events.py
mable/events/message_events.py
mable/events/reaction_events.py
mable/events/role_events.py
mable/events/scheduled_events.py
mable/events/shard_events.py
mable/events/typing_events.py
mable/events/user_events.py
mable/events/voice_events.py
mable/impl/__init__.py
mable/impl/bot.py
mable/impl/buckets.py
mable/impl/cache.py
mable/impl/config.py
mable/impl/entity_factory.py
mable/impl/event_factory.py
mable/impl/event_manager.py
mable/impl/event_manager_base.py
mable/impl/interaction_server.py
mable/impl/rate_limits.py
mable/impl/rest.py
mable/impl/rest_bot.py
mable/impl/shard.py
mable/impl/special_endpoints.py
mable/impl/voice.py
mable/interactions/__init__.py
mable/interactions/base_interactions.py
mable/interactions/command_interactions.py
mable/interactions/component_interactions.py
mable/interactions/modal_interactions.py
mable/internal/__init__.py
mable-2.1.2b1.dist-info/LICENSE
mable-2.1.2b1.dist-info/METADATA
mable-2.1.2b1.dist-info/WHEEL
mable-2.1.2b1.dist-info/entry_points.txt
mable-2.1.2b1.dist-info/top_level.txt
mable-2.1.2b1.dist-info/RECORD
