Metadata-Version: 2.1
Name: mable
Version: 2.1.2b1
Summary: Разумный Discord API для Python 3, построенный на asyncio и благих намерениях
Home-page: https://discord.gg/T2Mbw9u9gh
Author: MaseZev
Maintainer: MaseZev
Maintainer-email: csgomanagement@gmail.com
License: MIT
Project-URL: Discord, https://discord.gg/T2Mbw9u9gh
Classifier: Development Status :: 3 - Alpha
Classifier: Environment :: Console
Classifier: Framework :: AsyncIO
Classifier: Intended Audience :: Developers
Classifier: License :: OSI Approved :: MIT License
Classifier: Natural Language :: English
Classifier: Operating System :: OS Independent
Classifier: Programming Language :: Python :: 3.8
Classifier: Programming Language :: Python :: 3.9
Classifier: Programming Language :: Python :: 3.10
Classifier: Programming Language :: Python :: 3.11
Classifier: Programming Language :: Python :: Implementation :: CPython
Classifier: Topic :: Communications :: Chat
Classifier: Topic :: Internet :: WWW/HTTP
Classifier: Topic :: Software Development :: Libraries
Classifier: Topic :: Software Development :: Libraries :: Application Frameworks
Classifier: Topic :: Software Development :: Libraries :: Python Modules
Classifier: Typing :: Typed
Requires-Python: >=3.8,>=3.9,>=3.10,>=3.11
License-File: LICENSE
Requires-Dist: aiohttp (~=3.8)
Requires-Dist: attrs (~=22.2)
Requires-Dist: colorlog (~=6.7)
Requires-Dist: multidict (~=6.0)
Provides-Extra: server
Requires-Dist: pynacl (~=1.5) ; extra == 'server'
Provides-Extra: speedups
Requires-Dist: aiohttp[speedups] (~=3.8) ; extra == 'speedups'
Requires-Dist: ciso8601 (~=2.3) ; extra == 'speedups'
Requires-Dist: orjson (~=3.8) ; extra == 'speedups'
